botrun_pdf_to_text_rust-0.1.3.dist-info/METADATA
botrun_pdf_to_text_rust-0.1.3.dist-info/WHEEL
botrun_pdf_to_text_rust/__init__.py
botrun_pdf_to_text_rust/botrun_pdf_to_text_rust.cpython-311-darwin.so
botrun_pdf_to_text_rust-0.1.3.dist-info/RECORD
