Metadata-Version: 2.3
Name: botrun_pdf_to_text_rust
Version: 0.1.3
Summary: A package to extract text from PDF using Rust
Author-email: Bowen <cbh@cameo.tw>
License: MIT
